mo_parsing/__init__.py
mo_parsing/core.py
mo_parsing/debug.py
mo_parsing/enhancement.py
mo_parsing/exceptions.py
mo_parsing/expressions.py
mo_parsing/helpers.py
mo_parsing/infix.py
mo_parsing/profile.py
mo_parsing/regex.py
mo_parsing/results.py
mo_parsing/tokens.py
mo_parsing/utils.py
mo_parsing/whitespaces.py
mo_parsing-8.661.25011.dist-info/LICENSE
mo_parsing-8.661.25011.dist-info/METADATA
mo_parsing-8.661.25011.dist-info/WHEEL
mo_parsing-8.661.25011.dist-info/top_level.txt
mo_parsing-8.661.25011.dist-info/RECORD
