Metadata-Version: 2.2
Name: mo-parsing
Version: 8.661.25011
Summary: Another PEG Parsing Tool
Home-page: https://github.com/klahnakoski/mo-parsing
Author: Various
Author-email: kyle@lahnakoski.com
License: MIT
Classifier: Development Status :: 4 - Beta
Classifier: License :: OSI Approved :: MIT License
Classifier: Programming Language :: Python :: 3.8
Classifier: Programming Language :: Python :: 3.9
Classifier: Topic :: Software Development :: Libraries
Classifier: Topic :: Software Development :: Libraries :: Python Modules
Classifier: Programming Language :: Python :: 3.10
Classifier: Programming Language :: Python :: 3.11
Classifier: Programming Language :: Python :: 3.12
Classifier: Programming Language :: Python :: 3.13
License-File: LICENSE
Requires-Dist: mo-dots==10.659.25005
Requires-Dist: mo-future==7.584.24095
Provides-Extra: tests
Requires-Dist: mo-testing>=8.644.24152; extra == "tests"
Requires-Dist: mo-threads>=6.634.24139; extra == "tests"
Requires-Dist: mo-logs>=8.632.24139; extra == "tests"
Requires-Dist: mo-files>=6.638.24140; extra == "tests"
Dynamic: author
Dynamic: author-email
Dynamic: classifier
Dynamic: description
Dynamic: description-content-type
Dynamic: home-page
Dynamic: license
Dynamic: provides-extra
Dynamic: requires-dist
Dynamic: summary
